setup.py
Gaus_Bi_dis_vis/Binomialdistribution.py
Gaus_Bi_dis_vis/Gaussiandistribution.py
Gaus_Bi_dis_vis/Generaldistribution.py
Gaus_Bi_dis_vis/__init__.py
Gaus_Bi_dis_vis.egg-info/PKG-INFO
Gaus_Bi_dis_vis.egg-info/SOURCES.txt
Gaus_Bi_dis_vis.egg-info/dependency_links.txt
Gaus_Bi_dis_vis.egg-info/not-zip-safe
Gaus_Bi_dis_vis.egg-info/top_level.txt