Metadata-Version: 1.0
Name: Gaus-Bi-dis-vis
Version: 0.1.1
Summary: Gaussian and binomial distributions
Home-page: UNKNOWN
Author: Rahul Powar
Author-email: rahulpower2012@gmail.com
License: UNKNOWN
Platform: UNKNOWN
